{
    "_horizontalLines": 15.0,
    "_verticalLines": 17.0,
    "_radius": 0.09985001385211945,
    "_petalColour": {
        "r": 0.47893327474594118,
        "g": 0.9263277053833008,
        "b": 0.6964656114578247,
        "a": 1.0
    },
    "_cylinderVertexCount": 6.0,
    "_stemRadius": 0.051525168120861056,
    "_leafCount": 8.0,
    "_edgeRingCount": 42.0,
    "startPos": {
        "x": 0.0,
        "y": 0.0,
        "z": 0.0
    },
    "tangent1": {
        "x": -0.12246255576610565,
        "y": 1.7790937423706055,
        "z": -0.08985777199268341
    },
    "tangent2": {
        "x": -0.49029892683029177,
        "y": 2.346266269683838,
        "z": -0.05538525804877281
    },
    "endPos": {
        "x": -0.6467539668083191,
        "y": 4.0,
        "z": 0.555243730545044
    }
}