{
    "_horizontalLines": 17.0,
    "_verticalLines": 16.0,
    "_radius": 0.1129206046462059,
    "_petalColour": {
        "r": 0.8525062799453735,
        "g": 0.8473610877990723,
        "b": 0.009081244468688965,
        "a": 1.0
    },
    "_cylinderVertexCount": 11.0,
    "_stemRadius": 0.08830822259187699,
    "_leafCount": 8.0,
    "_edgeRingCount": 39.0,
    "startPos": {
        "x": 0.0,
        "y": 0.0,
        "z": 0.0
    },
    "tangent1": {
        "x": -0.26585808396339419,
        "y": 1.7504043579101563,
        "z": 0.08945055305957794
    },
    "tangent2": {
        "x": -0.6506191492080689,
        "y": 3.5508337020874025,
        "z": -0.35523146390914919
    },
    "endPos": {
        "x": -1.200443148612976,
        "y": 4.0,
        "z": -0.8495678901672363
    }
}