{
    "_horizontalLines": 19.0,
    "_verticalLines": 16.0,
    "_radius": 0.07054025679826737,
    "_petalColour": {
        "r": 0.1761990785598755,
        "g": 0.9542206525802612,
        "b": 0.33042651414871218,
        "a": 1.0
    },
    "_cylinderVertexCount": 9.0,
    "_stemRadius": 0.04552193731069565,
    "_leafCount": 8.0,
    "_edgeRingCount": 23.0,
    "startPos": {
        "x": 0.0,
        "y": 0.0,
        "z": 0.0
    },
    "tangent1": {
        "x": -0.2823673188686371,
        "y": 1.725189208984375,
        "z": -0.20642976462841035
    },
    "tangent2": {
        "x": -0.6867173910140991,
        "y": 3.5107293128967287,
        "z": -0.7048047780990601
    },
    "endPos": {
        "x": -0.26653942465782168,
        "y": 6.300000190734863,
        "z": -0.3082084357738495
    }
}