{
    "_horizontalLines": 16.0,
    "_verticalLines": 17.0,
    "_radius": 0.11879096180200577,
    "_petalColour": {
        "r": 0.4309006333351135,
        "g": 0.18908071517944337,
        "b": 0.21024513244628907,
        "a": 1.0
    },
    "_cylinderVertexCount": 6.0,
    "_stemRadius": 0.08185295015573502,
    "_leafCount": 8.0,
    "_edgeRingCount": 57.0,
    "startPos": {
        "x": 0.0,
        "y": 0.0,
        "z": 0.0
    },
    "tangent1": {
        "x": -0.033942509442567828,
        "y": 0.6958398222923279,
        "z": -0.4641231596469879
    },
    "tangent2": {
        "x": -0.030245400965213777,
        "y": 0.7874690294265747,
        "z": -0.8246271014213562
    },
    "endPos": {
        "x": -0.6306787133216858,
        "y": 4.0,
        "z": -0.9125505685806274
    }
}