{
    "_horizontalLines": 18.0,
    "_verticalLines": 15.0,
    "_radius": 0.0490313321352005,
    "_petalColour": {
        "r": 0.01611030101776123,
        "g": 0.5972577929496765,
        "b": 0.9892269372940064,
        "a": 1.0
    },
    "_cylinderVertexCount": 14.0,
    "_stemRadius": 0.025983761996030809,
    "_leafCount": 8.0,
    "_edgeRingCount": 48.0,
    "startPos": {
        "x": 0.0,
        "y": 0.0,
        "z": 0.0
    },
    "tangent1": {
        "x": -0.17142029106616975,
        "y": 0.7257415652275086,
        "z": -0.26258906722068789
    },
    "tangent2": {
        "x": -0.337242990732193,
        "y": 2.482978343963623,
        "z": -0.5577618479728699
    },
    "endPos": {
        "x": -1.095510721206665,
        "y": 5.150250434875488,
        "z": -0.8506933450698853
    }
}