{
    "_horizontalLines": 18.0,
    "_verticalLines": 18.0,
    "_radius": 0.07191416621208191,
    "_petalColour": {
        "r": 0.8149009943008423,
        "g": 0.6960389614105225,
        "b": 0.10602116584777832,
        "a": 1.0
    },
    "_cylinderVertexCount": 10.0,
    "_stemRadius": 0.033347830176353458,
    "_leafCount": 8.0,
    "_edgeRingCount": 7.0,
    "startPos": {
        "x": 0.0,
        "y": 0.0,
        "z": 0.0
    },
    "tangent1": {
        "x": -0.29765740036964419,
        "y": 1.2303794622421265,
        "z": -0.2826688289642334
    },
    "tangent2": {
        "x": -0.2672897279262543,
        "y": 2.470914363861084,
        "z": -0.28079038858413699
    },
    "endPos": {
        "x": 0.3406083881855011,
        "y": 4.0,
        "z": 0.348504900932312
    }
}