{
    "_horizontalLines": 18.0,
    "_verticalLines": 19.0,
    "_radius": 0.13585838675498963,
    "_petalColour": {
        "r": 0.177717924118042,
        "g": 0.9821985960006714,
        "b": 0.09587180614471436,
        "a": 1.0
    },
    "_cylinderVertexCount": 14.0,
    "_stemRadius": 0.09863750636577606,
    "_leafCount": 8.0,
    "_edgeRingCount": 7.0,
    "startPos": {
        "x": 0.0,
        "y": 0.0,
        "z": 0.0
    },
    "tangent1": {
        "x": 0.08237047493457794,
        "y": 0.943310558795929,
        "z": -0.1843399554491043
    },
    "tangent2": {
        "x": 0.4915556311607361,
        "y": 1.9556653499603272,
        "z": -0.07261601090431214
    },
    "endPos": {
        "x": 0.1748456060886383,
        "y": 4.0,
        "z": -0.25481611490249636
    }
}