{
    "_horizontalLines": 18.0,
    "_verticalLines": 17.0,
    "_radius": 0.036162957549095157,
    "_petalColour": {
        "r": 0.015032529830932618,
        "g": 0.034889936447143558,
        "b": 0.9673513174057007,
        "a": 1.0
    },
    "_cylinderVertexCount": 12.0,
    "_stemRadius": 0.017955483868718149,
    "_leafCount": 8.0,
    "_edgeRingCount": 64.0,
    "startPos": {
        "x": 0.0,
        "y": 0.0,
        "z": 0.0
    },
    "tangent1": {
        "x": 0.11367340385913849,
        "y": 1.9504162073135377,
        "z": -0.338575154542923
    },
    "tangent2": {
        "x": -0.37108170986175539,
        "y": 3.512709856033325,
        "z": -0.5127151012420654
    },
    "endPos": {
        "x": -0.6737418174743652,
        "y": 6.193823337554932,
        "z": 0.1422327756881714
    }
}