{
    "_horizontalLines": 18.0,
    "_verticalLines": 16.0,
    "_radius": 0.10693685710430145,
    "_petalColour": {
        "r": 0.2536999583244324,
        "g": 0.6564295291900635,
        "b": 0.7986843585968018,
        "a": 1.0
    },
    "_cylinderVertexCount": 5.0,
    "_stemRadius": 0.06310984492301941,
    "_leafCount": 8.0,
    "_edgeRingCount": 39.0,
    "startPos": {
        "x": 0.0,
        "y": 0.0,
        "z": 0.0
    },
    "tangent1": {
        "x": 0.08095808327198029,
        "y": 1.177355170249939,
        "z": 0.12177304923534394
    },
    "tangent2": {
        "x": -0.08449873328208924,
        "y": 3.1625983715057375,
        "z": 0.13437160849571229
    },
    "endPos": {
        "x": -0.12023729085922241,
        "y": 6.277618885040283,
        "z": -0.5039389133453369
    }
}