{
    "_horizontalLines": 17.0,
    "_verticalLines": 15.0,
    "_radius": 0.053479328751564029,
    "_petalColour": {
        "r": 0.9506436586380005,
        "g": 0.7767387628555298,
        "b": 0.1532973051071167,
        "a": 1.0
    },
    "_cylinderVertexCount": 7.0,
    "_stemRadius": 0.004895593039691448,
    "_leafCount": 8.0,
    "_edgeRingCount": 47.0,
    "startPos": {
        "x": 0.0,
        "y": 0.0,
        "z": 0.0
    },
    "tangent1": {
        "x": -0.28046178817749026,
        "y": 0.16460247337818147,
        "z": 0.23254737257957459
    },
    "tangent2": {
        "x": -0.6982987523078919,
        "y": 0.5411084890365601,
        "z": -0.18371525406837464
    },
    "endPos": {
        "x": -0.7886199355125427,
        "y": 4.0,
        "z": -0.6312804222106934
    }
}