{
    "_horizontalLines": 15.0,
    "_verticalLines": 16.0,
    "_radius": 0.107936792075634,
    "_petalColour": {
        "r": 0.8490097522735596,
        "g": 0.5014829039573669,
        "b": 0.10858678817749024,
        "a": 1.0
    },
    "_cylinderVertexCount": 5.0,
    "_stemRadius": 0.0970592349767685,
    "_leafCount": 8.0,
    "_edgeRingCount": 35.0,
    "startPos": {
        "x": 0.0,
        "y": 0.0,
        "z": 0.0
    },
    "tangent1": {
        "x": -0.1681496649980545,
        "y": 1.8716484308242798,
        "z": -0.2998937666416168
    },
    "tangent2": {
        "x": -0.5837195515632629,
        "y": 3.768122911453247,
        "z": -0.36493194103240969
    },
    "endPos": {
        "x": -1.0363056659698487,
        "y": 6.300000190734863,
        "z": 0.023556381464004518
    }
}